{
  "statistics": {
    "session": "prompt_basic",
    "duration": 2.0115251541137695,
    "total_energy_joules": 5.6022080898284905,
    "average_power_watts": 2.7850549511505815,
    "peak_power_watts": 5.571,
    "peak_temperature_celsius": 0.0,
    "peak_cpu_percent": 10.2,
    "peak_memory_percent": 77.6,
    "number_of_samples": 2
  },
  "snapshots": [
    {
      "timestamp": 1739780738.234024,
      "cpu_percent": 0.0,
      "memory_percent": 77.6,
      "power_consumption": 4.5,
      "temperature": 0.0,
      "disk_io": {
        "read_bytes": 524288,
        "write_bytes": 217088
      }
    },
    {
      "timestamp": 1739780739.239626,
      "cpu_percent": 10.2,
      "memory_percent": 77.6,
      "power_consumption": 5.571,
      "temperature": 0.0,
      "disk_io": {
        "read_bytes": 28672,
        "write_bytes": 372736
      }
    }
  ]
}